{
  "success": true,
  "model": [
    {
      "month": "1月",
      "count": 1100
    },
    {
      "month": "2月",
      "count": 1130
    },
    {
      "month": "3月",
      "count": 1400
    },
    {
      "month": "4月",
      "count": 2000
    },
    {
      "month": "5月",
      "count": 2600
    },
    {
      "month": "6月",
      "count": 1400
    },
    {
      "month": "7月",
      "count": 1300
    },
    {
      "month": "8月",
      "count": 1800
    },
    {
      "month": "9月",
      "count": 2200
    },
    {
      "month": "10月",
      "count": 2807
    },
    {
      "month": "11月",
      "count": 3917
    },
    {
      "month": "12月",
      "count": 3407
    }
  ]
}